autocontrastive_gen/__init__.py
autocontrastive_gen/contrast_calculation.py
autocontrastive_gen/run_inference.py
autocontrastive_gen/run_training.py
autocontrastive_gen/utils.py
autocontrastive_gen/data_processing/__init__.py
autocontrastive_gen/data_processing/dataset_catalog.py
autocontrastive_gen/data_processing/preprocessing_functions.py
autocontrastive_gen/evaluation/__init__.py
autocontrastive_gen/evaluation/auto_metrics.py
autocontrastive_gen/evaluation/lm_eval_harness/__init__.py
autocontrastive_gen/evaluation/lm_eval_harness/lm_eval_multi_head_gpt.py
autocontrastive_gen/evaluation/lm_eval_harness/run_lm_eval.py
autocontrastive_gen/head_training/__init__.py
autocontrastive_gen/head_training/gpt2_training.py
autocontrastive_gen/head_training/head_training_utils.py
autocontrastive_gen/head_training/t5_training.py
autocontrastive_gen/modeling/__init__.py
autocontrastive_gen/modeling/auto_model.py
autocontrastive_gen/modeling/configuration.py
autocontrastive_gen/modeling/gpt2_multi_head.py
autocontrastive_gen/modeling/gpt_neo_multi_head.py
autocontrastive_gen/modeling/t5_multi_head.py
autocontrastive_gen-0.2.0.dist-info/LICENSE
autocontrastive_gen-0.2.0.dist-info/METADATA
autocontrastive_gen-0.2.0.dist-info/WHEEL
autocontrastive_gen-0.2.0.dist-info/top_level.txt
autocontrastive_gen-0.2.0.dist-info/RECORD
