Metadata-Version: 2.1
Name: autocontrastive-gen
Version: 0.2.0
Summary: Auto-Contrastive Text Generation
Home-page: https://github.com/IBM/auto-contrastive-generation
Author: IBM Research
Author-email: ariel.gera1@ibm.com
License: Apache License 2.0
Classifier: Programming Language :: Python :: 3
Classifier: License :: OSI Approved :: Apache Software License
Classifier: Operating System :: OS Independent
Classifier: Topic :: Scientific/Engineering
Requires-Python: >=3.9
License-File: LICENSE
Requires-Dist: numpy (==1.24.2)
Requires-Dist: transformers (==4.26)
Requires-Dist: pandas (==1.5.3)
Requires-Dist: datasets (==2.4.0)
Requires-Dist: torch (==1.11.0)
Requires-Dist: lm-eval (==0.3.0)
